{
  "main": {
    "id": "faab003465a9fa4d",
    "type": "split",
    "children": [
      {
        "id": "ed47b5ded27b3d21",
        "type": "tabs",
        "children": [
          {
            "id": "ecbb70e0fa458bc0",
            "type": "leaf",
            "state": {
              "type": "empty",
              "state": {}
            }
          }
        ]
      }
    ],
    "direction": "vertical"
  },
  "left": {
    "id": "ac051de70d775e65",
    "type": "split",
    "children": [
      {
        "id": "7526406559c953d5",
        "type": "tabs",
        "children": [
          {
            "id": "7e1a2d5c9acd3ddc",
            "type": "leaf",
            "state": {
              "type": "file-explorer",
              "state": {
                "sortOrder": "alphabetical"
              }
            }
          },
          {
            "id": "795924ffc8f6eb75",
            "type": "leaf",
            "state": {
              "type": "search",
              "state": {
                "query": "real ",
                "matchingCase": true,
                "explainSearch": false,
                "collapseAll": false,
                "extraContext": false,
                "sortOrder": "alphabetical"
              }
            }
          },
          {
            "id": "4e1a06009cc14b97",
            "type": "leaf",
            "state": {
              "type": "bookmarks",
              "state": {}
            }
          }
        ]
      },
      {
        "id": "0e7524ded4d579dd",
        "type": "tabs",
        "children": [
          {
            "id": "e9ebb2500332dce0",
            "type": "leaf",
            "state": {
              "type": "localgraph",
              "state": {
                "options": {
                  "collapse-filter": true,
                  "search": "",
                  "localJumps": 1,
                  "localBacklinks": true,
                  "localForelinks": true,
                  "localInterlinks": false,
                  "showTags": false,
                  "showAttachments": false,
                  "hideUnresolved": false,
                  "collapse-color-groups": true,
                  "colorGroups": [],
                  "collapse-display": true,
                  "showArrow": false,
                  "textFadeMultiplier": 0,
                  "nodeSizeMultiplier": 1,
                  "lineSizeMultiplier": 1,
                  "collapse-forces": true,
                  "centerStrength": 0.518713248970312,
                  "repelStrength": 10,
                  "linkStrength": 1,
                  "linkDistance": 250,
                  "scale": 0.5784646179408367,
                  "close": true
                }
              }
            }
          }
        ]
      }
    ],
    "direction": "horizontal",
    "width": 287.5
  },
  "right": {
    "id": "07cd03c07b9eaf2f",
    "type": "split",
    "children": [
      {
        "id": "8f895e9e0285e8c9",
        "type": "tabs",
        "children": [
          {
            "id": "261c4b9be22b609a",
            "type": "leaf",
            "state": {
              "type": "backlink",
              "state": {
                "collapseAll": false,
                "extraContext": false,
                "sortOrder": "alphabetical",
                "showSearch": false,
                "searchQuery": "",
                "backlinkCollapsed": false,
                "unlinkedCollapsed": true
              }
            }
          },
          {
            "id": "21f749ca6f782178",
            "type": "leaf",
            "state": {
              "type": "outgoing-link",
              "state": {
                "linksCollapsed": false,
                "unlinkedCollapsed": true
              }
            }
          },
          {
            "id": "81ebdd553cb69d97",
            "type": "leaf",
            "state": {
              "type": "tag",
              "state": {
                "sortOrder": "frequency",
                "useHierarchy": true
              }
            }
          },
          {
            "id": "0880bd0c6130b8a7",
            "type": "leaf",
            "state": {
              "type": "outline",
              "state": {}
            }
          },
          {
            "id": "9142bb1339c72db2",
            "type": "leaf",
            "state": {
              "type": "graph",
              "state": {}
            }
          },
          {
            "id": "aaf2c78f3533220c",
            "type": "leaf",
            "state": {
              "type": "advanced-tables-toolbar",
              "state": {}
            }
          }
        ],
        "currentTab": 5
      }
    ],
    "direction": "horizontal",
    "width": 468.5,
    "collapsed": true
  },
  "left-ribbon": {
    "hiddenItems": {
      "graph:Open graph view": false,
      "switcher:Open quick switcher": false,
      "canvas:Create new canvas": false,
      "daily-notes:Open today's daily note": false,
      "templates:Insert template": false,
      "command-palette:Open command palette": false,
      "darlal-switcher-plus:Open in Headings Mode": false,
      "darlal-switcher-plus:Open Symbols for the active editor": false,
      "obsidian-excalidraw-plugin:Create new drawing": false,
      "table-editor-obsidian:Advanced Tables Toolbar": false
    }
  },
  "active": "ecbb70e0fa458bc0",
  "lastOpenFiles": [
    "Sistemas Operativos/Apuntes/senales.pdf",
    "Sistemas Operativos/Señales.md",
    "Estructuras II/Razonando con Programas.md",
    "Inducción.md",
    "Estructuras II/Arboles.md",
    "Estructuras II/Libros/okasaki.pdf",
    "Estructuras II/Tipos Abstractos de Datos.md",
    "Estructuras II/Estructuras II.md",
    "Sistemas Operativos/NachOS.md",
    "Sistemas Operativos/Libros/Fundamentos de los sistemas operativos.pdf",
    "Sistemas Operativos/Planificación/Planificación.md",
    "Excalidraw/Drawing 2024-05-07 09.11.54.excalidraw.md",
    "Sistemas Operativos/Sistema Operativo.md",
    "Sistemas Operativos/Sistemas Operativos.md",
    "Procesos.md",
    "Sistemas Operativos/Procesadores.md",
    "2024-05-05.md",
    "Sistemas Operativos/Planificación/Planificación a Corto Plazo.md",
    "Sistemas Operativos/Apuntes/linux_scheduler.pdf",
    "Sistemas Operativos/Hilos.md",
    "Sistemas Operativos/Proceso.md",
    "Sistemas Operativos/Task.md",
    "Planificación en tiempo real.md",
    "Untitled 1.md",
    "procesador.md",
    "HTB/Hydra.md",
    "Untitled.md",
    "HTB/Brute Forcing.md",
    "Passwords.md",
    "Sistemas Operativos/Planificación",
    "Pasted image 20240502173636.png",
    "Pasted image 20240502173051.png",
    "Pasted image 20240502172806.png",
    "Fotos/Pasted image 20240501162236.png",
    "Fotos/Pasted image 20240501161120.png",
    "Fotos/Pasted image 20240501160734.png",
    "Fotos/Pasted image 20240430143132.png",
    "Estructuras II/Libros",
    "Sistemas Operativos/Libros/Andrew S. Tanenbaum - Operating Systems. Design and Implementation.pdf",
    "Sistemas Operativos/Apuntes/virtualizacion.pdf",
    "Sistemas Operativos/Libros/OSTEP.txt",
    "Sistemas Operativos/Libros",
    "Fotos/Pasted image 20240414183031.png",
    "Fotos/Pasted image 20240414182323.png",
    "Fotos/wfuzz.svg"
  ]
}